rocket_tarikbenaouda/__init__.py
rocket_tarikbenaouda/rocket.py
rocket_tarikbenaouda-1.0.0.dist-info/LICENSE.txt
rocket_tarikbenaouda-1.0.0.dist-info/METADATA
rocket_tarikbenaouda-1.0.0.dist-info/WHEEL
rocket_tarikbenaouda-1.0.0.dist-info/top_level.txt
rocket_tarikbenaouda-1.0.0.dist-info/RECORD
