Metadata-Version: 2.1
Name: rocket_tarikbenaouda
Version: 1.0.0
Summary: An awesome package that does something
Home-page: http://pypi.python.org/pypi/rocket/
Author: tarikbenaouda
Author-email: ta.benaouda@esi-sba.dx
License: LICENSE.txt
License-File: LICENSE.txt
Requires-Dist: rocket-tarikbenaouda
